{
    "venvPath": ".",
    "venv": ".venv",
    "pythonVersion": "3.14",
    "pythonPlatform": "Windows",
    "pythonPath": "${workspaceFolder}/.venv/Scripts/python.exe",
    "typeCheckingMode": "off",
    "include": [
        "server",
        "env",
        "agent",
        "."
    ],
    "exclude": [
        ".venv",
        "**/__pycache__",
        "**/.pytest_cache",
        "**/.git",
        "**/.vscode",
        "**/.*",
        "**/node_modules",
        "**/.idea",
        "**/build",
        "**/dist",
        "**/*.egg-info"
    ],
    "reportMissingImports": false,
    "reportMissingTypeStubs": false
}
        "**/node_modules",
        "**/.idea",
        "**/build",
        "**/dist",
        "**/*.egg-info"
    ]
}
